callout_transformer/__init__.py
callout_transformer/__main__.py
callout_transformer/cli.py
callout_transformer-0.1.0.dist-info/LICENSE
callout_transformer-0.1.0.dist-info/METADATA
callout_transformer-0.1.0.dist-info/WHEEL
callout_transformer-0.1.0.dist-info/entry_points.txt
callout_transformer-0.1.0.dist-info/top_level.txt
callout_transformer-0.1.0.dist-info/RECORD
